las/__init__.py
las/catalog/__init__.py
las/catalog/core/__init__.py
las/catalog/core/api.py
las/catalog/core/catalog_client.py
las/catalog/core/client.py
las/catalog/core/exception.py
las/catalog/core/model.py
las/catalog/core/entity/__init__.py
las/catalog/core/entity/catalog.py
las/catalog/core/entity/database.py
las/catalog/core/entity/database_builder.py
las/catalog/core/entity/table.py
las/catalog/core/entity/table_builder.py
las/catalog/request/__init__.py
las/catalog/request/catalog/__init__.py
las/catalog/request/catalog/api.py
las/catalog/request/catalog/model.py
las/catalog/request/operator/__init__.py
las/catalog/request/operator/api.py
las/catalog/request/optimizer/__init__.py
las/catalog/request/optimizer/api.py
las/catalog/request/partition/__init__.py
las/catalog/request/schema/__init__.py
las/catalog/request/schema/api.py
las/catalog/request/table/__init__.py
las/catalog/request/table/api.py
las/catalog/request/volume/__init__.py
las/catalog/request/volume/api.py
las/catalog/utils/__init__.py
las/catalog/utils/signature.py
las/catalog/utils/tool.py
lascatalog-1.0.2.dist-info/LICENSE
lascatalog-1.0.2.dist-info/METADATA
lascatalog-1.0.2.dist-info/WHEEL
lascatalog-1.0.2.dist-info/top_level.txt
lascatalog-1.0.2.dist-info/RECORD
